panorama_openedx_backend/__init__.py
panorama_openedx_backend/admin.py
panorama_openedx_backend/apps.py
panorama_openedx_backend/models.py
panorama_openedx_backend/urls.py
panorama_openedx_backend/utils.py
panorama_openedx_backend/views.py
panorama_openedx_backend/aws_sigv4_query/__init__.py
panorama_openedx_backend/aws_sigv4_query/api.py
panorama_openedx_backend/migrations/0001_initial.py
panorama_openedx_backend/migrations/0002_useraccessconfiguration_role.py
panorama_openedx_backend/migrations/0003_delete_panorama_config_and_more.py
panorama_openedx_backend/migrations/0004_dashboard_priority.py
panorama_openedx_backend/migrations/__init__.py
panorama_openedx_backend/settings/__init__.py
panorama_openedx_backend/settings/common.py
panorama_openedx_backend/templates/panorama_openedx_backend/base.html
test_utils/__init__.py
panorama_openedx_backend-16.1.0.dist-info/LICENSE.txt
panorama_openedx_backend-16.1.0.dist-info/METADATA
panorama_openedx_backend-16.1.0.dist-info/WHEEL
panorama_openedx_backend-16.1.0.dist-info/entry_points.txt
panorama_openedx_backend-16.1.0.dist-info/top_level.txt
panorama_openedx_backend-16.1.0.dist-info/RECORD
