Metadata-Version: 2.1
Name: panorama-openedx-backend
Version: 16.1.0
Summary: Django app that implements backend functions for Panorama MFE
Home-page: https://github.com/aulasneo/panorama-openedx-backend
Author: Aulasneo
Author-email: andres@aulasneo.com
Keywords: Panorama openedx backend MFE
Classifier: Development Status :: 3 - Alpha
Classifier: Framework :: Django
Classifier: Framework :: Django :: 3.2
Classifier: Intended Audience :: Developers
Classifier: License :: Other/Proprietary License
Classifier: Natural Language :: English
Classifier: Programming Language :: Python :: 3
Classifier: Programming Language :: Python :: 3.8
Requires-Python: >=3.8
License-File: LICENSE.txt
Requires-Dist: Django
Requires-Dist: boto3 ==1.34.87
Requires-Dist: django-model-utils
Requires-Dist: django-rest-framework
Requires-Dist: openedx-atlas
Requires-Dist: requests
